FFfilter-0.0.1.dist-info/DESCRIPTION.rst
FFfilter-0.0.1.dist-info/METADATA
FFfilter-0.0.1.dist-info/RECORD
FFfilter-0.0.1.dist-info/WHEEL
FFfilter-0.0.1.dist-info/entry_points.txt
FFfilter-0.0.1.dist-info/metadata.json
FFfilter-0.0.1.dist-info/top_level.txt
fffilter/__init__.py
fffilter/fffilter.py
