Metadata-Version: 2.0
Name: FFfilter
Version: 0.0.1
Summary: Filters media files by testing criteria against header metadata extracted by ffprobe.
Home-page: UNKNOWN
Author: Edward Anderson
Author-email: edward.anderson@bfi.org.uk
License: Attribution-NonCommercial-ShareAlike 4.0 International (CC BY-NC-SA 4.0)
Platform: UNKNOWN
Requires-Dist: colorama
